README.rst
setup.py
conditioned_profile.egg-info/PKG-INFO
conditioned_profile.egg-info/SOURCES.txt
conditioned_profile.egg-info/dependency_links.txt
conditioned_profile.egg-info/entry_points.txt
conditioned_profile.egg-info/not-zip-safe
conditioned_profile.egg-info/top_level.txt
condprof/__init__.py
condprof/android.py
condprof/archiver.py
condprof/changelog.py
condprof/check_install.py
condprof/client.py
condprof/creator.py
condprof/desktop.py
condprof/helpers.py
condprof/metadata.py
condprof/progress.py
condprof/runner.py
condprof/util.py
condprof/customization/__init__.py
condprof/scenarii/__init__.py
condprof/scenarii/heavy.py
condprof/scenarii/settled.py
condprof/tests/__init__.py
condprof/tests/fakefirefox.py
condprof/tests/fakegeckodriver.py
condprof/tests/test_client.py
condprof/tests/test_runner.py