Metadata-Version: 1.0
Name: conditioned-profile
Version: 0.2
Summary: Firefox Heavy Profile creator
Home-page: UNKNOWN
Author: UNKNOWN
Author-email: UNKNOWN
License: UNKNOWN
Platform: UNKNOWN
